{
  "$schema": "https://mintlify.com/docs.json",
  "name": "MetaMap Android SDK",
  "theme": "palm",
  "colors": {
    "primary": "#444444",
    "light": "#e78465",
    "dark": "#65cff4"
  },
  "favicon": "https://media.brand.dev/12f11e2d-fe67-484a-aa38-454145ae8c23.png",
  "logo": {
    "light": "https://media.brand.dev/f222c358-536e-4adb-bcb8-9f0abb732522.svg",
    "dark": "https://media.brand.dev/f222c358-536e-4adb-bcb8-9f0abb732522.svg"
  },
  "navbar": {
    "primary": {
      "type": "github",
      "href": "https://github.com/GetMetaMap/metamap-android-sdk"
    }
  },
  "footer": {
    "socials": {
      "github": "https://github.com/GetMetaMap/metamap-android-sdk"
    }
  },
  "navigation": {
    "tabs": [
      {
        "tab": "Documentation",
        "groups": [
          {
            "group": "Get Started",
            "pages": [
              "introduction",
              "installation",
              "quickstart"
            ]
          },
          {
            "group": "Integration Guides",
            "pages": [
              "guides/basic-integration",
              "guides/metamap-button",
              "guides/result-handling",
              "guides/metadata"
            ]
          },
          {
            "group": "Customization",
            "pages": [
              "customization/ui-colors",
              "customization/fonts",
              "customization/language"
            ]
          },
          {
            "group": "Advanced Features",
            "pages": [
              "advanced/face-match",
              "advanced/smart-capture",
              "advanced/encryption",
              "advanced/cooldown"
            ]
          }
        ]
      },
      {
        "tab": "API Reference",
        "groups": [
          {
            "group": "Core Classes",
            "pages": [
              "api/metamap-sdk",
              "api/metamap-button",
              "api/metadata"
            ]
          },
          {
            "group": "Configuration",
            "pages": [
              "api/ui-config",
              "api/font-config"
            ]
          }
        ]
      }
    ]
  }
}
